<?xml version="1.0" encoding="utf-8"?>
<!DOCTYPE hibernate-mapping PUBLIC "-//Hibernate/Hibernate Mapping DTD 3.0//EN"
"http://hibernate.sourceforge.net/hibernate-mapping-3.0.dtd">
<!-- 
    Mapping file autogenerated by MyEclipse Persistence Tools
-->
<hibernate-mapping>
    <class name="net.chinanets.pojos.Menus" table="MENUS" >
        <id name="id" type="java.lang.Long">
            <column name="ID" precision="22" scale="0" />
            <generator class="increment" />
        </id>
        <many-to-one name="menus" class="net.chinanets.pojos.Menus" fetch="select">
            <column name="PARENT_ID" precision="22" scale="0" />
        </many-to-one>
        <property name="mc" type="java.lang.String">
            <column name="MC" length="20" />
        </property>
        <property name="url" type="java.lang.String">
            <column name="URL" length="100" />
        </property>
        <property name="bz" type="java.lang.String">
            <column name="BZ" length="4000" />
        </property>
        <property name="pageUrl" type="java.lang.String">
            <column name="PAGEURL" length="100" />
        </property>
        <property name="menuImg" type="java.lang.String">
            <column name="MENU_IMG" length="225" />
        </property>
        <bag name="rulesMenuses" inverse="true" cascade="all">
            <key>
                <column name="MENU_ID" precision="22" scale="0" not-null="true" />
            </key>
            <one-to-many class="net.chinanets.pojos.RulesMenus" />
        </bag>
        <bag name="menuses" inverse="true" >
            <key>
                <column name="PARENT_ID" precision="22" scale="0" />
            </key>
            <one-to-many class="net.chinanets.pojos.Menus" />
        </bag>
                 <bag name="usersMenuses" inverse="true" cascade="all">
            <key>
                <column name="MENU_ID" precision="22" scale="0" not-null="true" />
            </key>
            <one-to-many class="net.chinanets.pojos.UsersMenus" />
        </bag>
        
    </class>
</hibernate-mapping>
